Pix_Chan/__init__.py
Pix_Chan/main.py
aiopix_chan-1.0.1.dist-info/LICENSE
aiopix_chan-1.0.1.dist-info/METADATA
aiopix_chan-1.0.1.dist-info/WHEEL
aiopix_chan-1.0.1.dist-info/top_level.txt
aiopix_chan-1.0.1.dist-info/RECORD
