Metadata-Version: 2.1
Name: aiopix-chan
Version: 1.0.1
Summary: Asynchronous version of Pix-Chan
Author-email: nennneko5787 <h4369@nennneko5787.net>
Project-URL: Homepage, https://github.com/nennneko5787/aiopix-chan
Project-URL: Issues, https://github.com/nennneko5787/aiopix-chan/issues
Classifier: Programming Language :: Python :: 3
Classifier: License :: OSI Approved :: GNU Affero General Public License v3
Classifier: Operating System :: OS Independent
Classifier: Natural Language :: Japanese
Requires-Python: >=3.8
License-File: LICENSE
Requires-Dist: httpx
